dataplot/__init__.py
dataplot/__version__.py
dataplot/_typing.py
dataplot/container.py
dataplot/core.py
dataplot/dataset.py
dataplot/setting.py
dataplot/artist/__init__.py
dataplot/artist/base.py
dataplot/artist/corrmap.py
dataplot/artist/histogram.py
dataplot/artist/ksplot.py
dataplot/artist/linechart.py
dataplot/artist/ppplot.py
dataplot/artist/qqplot.py
dataplot/utils/__init__.py
dataplot/utils/math.py
dataplot/utils/multi.py
dataplot-0.1.5.dist-info/LICENSE
dataplot-0.1.5.dist-info/METADATA
dataplot-0.1.5.dist-info/WHEEL
dataplot-0.1.5.dist-info/top_level.txt
dataplot-0.1.5.dist-info/RECORD
