Metadata-Version: 2.1
Name: dataplot
Version: 0.1.5
Summary: Provides plotting tools useful in datascience.
Home-page: https://github.com/Chitaoji/dataplot/
Author: Chitaoji
Author-email: 2360742040@qq.com
License: BSD
Platform: UNKNOWN
Classifier: License :: OSI Approved :: BSD License
Classifier: Programming Language :: Python
Classifier: Programming Language :: Python :: 3.11
Classifier: Programming Language :: Python :: 3.12
Requires-Python: >=3.11.9
Requires-Dist: hintwith
Requires-Dist: lazyr
Requires-Dist: matplotlib
Requires-Dist: numpy
Requires-Dist: pandas
Requires-Dist: scipy
Requires-Dist: seaborn
